{"VerifiedEmail":0,"TotalEmailRegistered":0,"TshirtGot":0,"Start":1452973508,"TargetTshirt":120,"Emails":{"syb10@2doo.net":{"id":8676754,"email":"syb10@2doo.net","social_id":"88SCJ","social_url":"http://iamnotbasic.kickoffpages.com/?kid=88SCJ","redirect_url":"http://kampanya.kickoffpages.com?kolid=88SCJ","unverified_leads":{"indirect":512,"direct":88},"verified_leads":{"indirect":336,"direct":57},"influence":{"indirect":336,"direct":57},"subscription_number":26671,"uid":"9C68084F-1819-4F7E-9D51-7E5B832A54EA","rank":26671,"counter":1,"lead_count":43687,"list_id":63710},"syb1@2doo.net":{"id":8676596,"email":"syb1@2doo.net","social_id":"88S7M","social_url":"http://iamnotbasic.kickoffpages.com/?kid=88S7M","redirect_url":"http://kampanya.kickoffpages.com?kolid=88S7M","unverified_leads":{"indirect":178,"direct":98},"verified_leads":{"indirect":74,"direct":51},"influence":{"indirect":74,"direct":51},"subscription_number":26550,"uid":"443A5701-17C7-47DD-8036-1B6EF0E84F06","rank":26550,"counter":1,"lead_count":43687,"list_id":63710},"syb2@2doo.net":{"id":8676624,"email":"syb2@2doo.net","social_id":"88S8G","social_url":"http://iamnotbasic.kickoffpages.com/?kid=88S8G","redirect_url":"http://kampanya.kickoffpages.com?kolid=88S8G","unverified_leads":{"indirect":360,"direct":89},"verified_leads":{"indirect":192,"direct":53},"influence":{"indirect":192,"direct":53},"subscription_number":26570,"uid":"443A5701-17C7-47DD-8036-1B6EF0E84F06","rank":26570,"counter":1,"lead_count":43687,"list_id":63710},"syb3@2doo.net":{"id":8676677,"email":"syb3@2doo.net","social_id":"88SA5","social_url":"http://iamnotbasic.kickoffpages.com/?kid=88SA5","redirect_url":"http://kampanya.kickoffpages.com?kolid=88SA5","unverified_leads":{"indirect":170,"direct":92},"verified_leads":{"indirect":93,"direct":55},"influence":{"indirect":93,"direct":55},"subscription_number":26610,"uid":"E399F367-3F97-46E1-9CBF-75A9314FF64F","rank":26610,"counter":1,"lead_count":43687,"list_id":63710},"syb4@2doo.net":{"id":8676690,"email":"syb4@2doo.net","social_id":"88SAJ","social_url":"http://iamnotbasic.kickoffpages.com/?kid=88SAJ","redirect_url":"http://kampanya.kickoffpages.com?kolid=88SAJ","unverified_leads":{"indirect":158,"direct":77},"verified_leads":{"indirect":85,"direct":55},"influence":{"indirect":85,"direct":55},"subscription_number":26621,"uid":"E399F367-3F97-46E1-9CBF-75A9314FF64F","rank":26621,"counter":1,"lead_count":43493,"list_id":63710},"syb5@2doo.net":{"id":8676697,"email":"syb5@2doo.net","social_id":"88SAS","social_url":"http://iamnotbasic.kickoffpages.com/?kid=88SAS","redirect_url":"http://kampanya.kickoffpages.com?kolid=88SAS","unverified_leads":{"indirect":125,"direct":96},"verified_leads":{"indirect":61,"direct":51},"influence":{"indirect":61,"direct":51},"subscription_number":26626,"uid":"9C68084F-1819-4F7E-9D51-7E5B832A54EA","rank":26626,"counter":1,"lead_count":43493,"list_id":63710},"syb6@2doo.net":{"id":8676710,"email":"syb6@2doo.net","social_id":"88SB6","social_url":"http://iamnotbasic.kickoffpages.com/?kid=88SB6","redirect_url":"http://kampanya.kickoffpages.com?kolid=88SB6","unverified_leads":{"indirect":112,"direct":89},"verified_leads":{"indirect":58,"direct":49},"influence":{"indirect":58,"direct":49},"subscription_number":26637,"uid":"9C68084F-1819-4F7E-9D51-7E5B832A54EA","rank":26637,"counter":1,"lead_count":43687,"list_id":63710},"syb7@2doo.net":{"id":8676719,"email":"syb7@2doo.net","social_id":"88SBF","social_url":"http://iamnotbasic.kickoffpages.com/?kid=88SBF","redirect_url":"http://kampanya.kickoffpages.com?kolid=88SBF","unverified_leads":{"indirect":108,"direct":89},"verified_leads":{"indirect":50,"direct":45},"influence":{"indirect":50,"direct":45},"subscription_number":26644,"uid":"9C68084F-1819-4F7E-9D51-7E5B832A54EA","rank":26644,"counter":1,"lead_count":43721,"list_id":63710},"syb8@2doo.net":{"id":8676734,"email":"syb8@2doo.net","social_id":"88SBY","social_url":"http://iamnotbasic.kickoffpages.com/?kid=88SBY","redirect_url":"http://kampanya.kickoffpages.com?kolid=88SBY","unverified_leads":{"indirect":56,"direct":51},"verified_leads":{"indirect":20,"direct":19},"influence":{"indirect":20,"direct":19},"subscription_number":26654,"uid":"9C68084F-1819-4F7E-9D51-7E5B832A54EA","rank":26654,"counter":1,"lead_count":43721,"list_id":63710},"syb9@2doo.net":{"id":8676745,"email":"syb9@2doo.net","social_id":"88SC9","social_url":"http://iamnotbasic.kickoffpages.com/?kid=88SC9","redirect_url":"http://kampanya.kickoffpages.com?kolid=88SC9","unverified_leads":{"indirect":0,"direct":0},"verified_leads":{"indirect":0,"direct":0},"influence":{"indirect":0,"direct":0},"subscription_number":26663,"uid":"9C68084F-1819-4F7E-9D51-7E5B832A54EA","rank":26663,"counter":1,"lead_count":43493,"list_id":63710}}}